{
  "$schema": "https://developer.microsoft.com/json-schemas/fabric/item/report/definition/visualContainer/1.0.0/schema.json",
  "name": "7ee7e36d0304988a6805",
  "position": {
    "x": 704.68817204301081,
    "y": 23.397849462365592,
    "z": 2000,
    "width": 210.58064516129033,
    "height": 88.086021505376351,
    "tabOrder": 2000
  },
  "visual": {
    "visualType": "slicer",
    "query": {
      "queryState": {
        "Values": {
          "projections": [
            {
              "field": {
                "Column": {
                  "Expression": {
                    "SourceRef": {
                      "Entity": "data"
                    }
                  },
                  "Property": "DISAGMOT"
                }
              },
              "queryRef": "data.DISAGMOT",
              "nativeQueryRef": "Mode of Transportation",
              "active": true,
              "displayName": "Mode of Transportation"
            }
          ]
        }
      }
    },
    "objects": {
      "data": [
        {
          "properties": {
            "mode": {
              "expr": {
                "Literal": {
                  "Value": "'Dropdown'"
                }
              }
            }
          }
        }
      ],
      "general": [
        {
          "properties": {}
        }
      ]
    },
    "visualContainerObjects": {
      "dropShadow": [
        {
          "properties": {
            "show": {
              "expr": {
                "Literal": {
                  "Value": "true"
                }
              }
            },
            "position": {
              "expr": {
                "Literal": {
                  "Value": "'Outer'"
                }
              }
            },
            "color": {
              "solid": {
                "color": {
                  "expr": {
                    "Literal": {
                      "Value": "'#12239e'"
                    }
                  }
                }
              }
            }
          }
        }
      ]
    },
    "drillFilterOtherVisuals": true
  }
}